dcckit/__init__.py
dcckit/host.py
dcckit/math.py
dcckit/qt.py
dcckit/scene.py
dcckit/houdini/__init__.py
dcckit/houdini/marshal.py
dcckit/max/__init__.py
dcckit/max/geometry.py
dcckit/max/interface.py
dcckit/max/marshal.py
dcckit/max/materials.py
dcckit/max/paths.py
dcckit/max/plugins.py
dcckit/max/export/__init__.py
dcckit/max/sdk/__init__.py
dcckit/max/sdk/inode.py
dcckit/max/utils/__init__.py
dcckit/max/utils/ats.py
dcckit/max/utils/coordsys.py
dcckit/max/utils/layers.py
dcckit/max/utils/node.py
dcckit/max/utils/selection.py
dcckit/max/utils/selection_set.py
dcckit/max/utils/viewport.py
dcckit/unreal/__init__.py
dcckit/unreal/engine.py
dcckit/unreal/plugin.py
dcckit/unreal/project.py
dcckit-0.0.5.dist-info/LICENSE
dcckit-0.0.5.dist-info/METADATA
dcckit-0.0.5.dist-info/WHEEL
dcckit-0.0.5.dist-info/top_level.txt
dcckit-0.0.5.dist-info/RECORD
