Metadata-Version: 2.1
Name: dcckit
Version: 0.0.5
Summary: Description
Home-page: https://github.com/Bailey3D/dcc-kit
Author: Bailey3D
Author-email: bailey@bailey3d.com
License: MIT
Keywords: dcckit
Classifier: Development Status :: 3 - Alpha
Classifier: License :: OSI Approved :: MIT License
Classifier: Programming Language :: Python :: 3
Classifier: Operating System :: OS Independent
License-File: LICENSE
Requires-Dist: numpy
Requires-Dist: pythonnet
Requires-Dist: qtpy
Requires-Dist: scipy
